terrorform/__init__.py
terrorform/terrorform.py
terrorform-0.2.1.dist-info/LICENSE
terrorform-0.2.1.dist-info/METADATA
terrorform-0.2.1.dist-info/WHEEL
terrorform-0.2.1.dist-info/top_level.txt
terrorform-0.2.1.dist-info/RECORD
