Metadata-Version: 2.1
Name: terrorform
Version: 0.2.1
Summary: Terraform wrapper for python
Home-page: https://github.com/bengetch/terrorform
Author: bengetch
Author-email: bengetch@gmail.com
License: MIT
Requires-Python: >=3.5
License-File: LICENSE
Requires-Dist: pytest
